o3r_algo_utilities/__init__.py
o3r_algo_utilities/o3r_uncompress_di.py
o3r_algo_utilities/rotmat.py
o3r_algo_utilities/calib/__init__.py
o3r_algo_utilities/calib/calibration.py
o3r_algo_utilities/calib/corner_detector.py
o3r_algo_utilities/calib/point_correspondences.py
o3r_algo_utilities/calib/sources.py
o3r_algo_utilities-1.1.2.dist-info/LICENSE
o3r_algo_utilities-1.1.2.dist-info/METADATA
o3r_algo_utilities-1.1.2.dist-info/NOTICE
o3r_algo_utilities-1.1.2.dist-info/WHEEL
o3r_algo_utilities-1.1.2.dist-info/top_level.txt
o3r_algo_utilities-1.1.2.dist-info/RECORD
