Metadata-Version: 2.1
Name: o3r-algo-utilities
Version: 1.1.2
Summary: Algorithm examples related to the ifm O3R product.
Home-page: UNKNOWN
License: Apache 2.0 License
Keywords: ifm,o3r,point_cloud
Platform: UNKNOWN
Classifier: License :: OSI Approved :: Apache Software License
Classifier: Programming Language :: Python :: 3
Requires-Dist: numpy (>=1.11.0)
Requires-Dist: opencv-python (>=4.5.3)
Requires-Dist: scipy (>=1.7)
Requires-Dist: h5py (>=3.2)
Requires-Dist: matplotlib (>=3.4)
Provides-Extra: ifm3dpy
Requires-Dist: ifm3dpy (>=1.2.6) ; extra == 'ifm3dpy'
Provides-Extra: imeas
Requires-Dist: ifm-imeas (>=4.0) ; extra == 'imeas'
Requires-Dist: six ; extra == 'imeas'
Provides-Extra: jupyter
Requires-Dist: jupyterlab (>=3.1) ; extra == 'jupyter'
Requires-Dist: ipympl (>=0.7.0) ; extra == 'jupyter'
